dash_flow/DashFlow.py
dash_flow/__init__.py
dash_flow/_imports_.py
dash_flow/dash_flow.min.js
dash_flow/dash_flow.min.js.map
dash_flow/metadata.json
dash_flow/package-info.json
dash_flow-0.0.5.dist-info/LICENSE
dash_flow-0.0.5.dist-info/METADATA
dash_flow-0.0.5.dist-info/WHEEL
dash_flow-0.0.5.dist-info/top_level.txt
dash_flow-0.0.5.dist-info/RECORD
