Metadata-Version: 2.1
Name: dash-flow
Version: 0.0.5
Summary: React Flow on Dash
Author: Shin Ah Oh <i.am.hemidemisemiquaver@gmail.com>
License: MIT
Platform: UNKNOWN
Classifier: Framework :: Dash
License-File: LICENSE
